sonar_api_wrapper/__init__.py
sonar_api_wrapper/__version__.py
sonar_api_wrapper/client.py
sonar_api_wrapper-1.3.0.dist-info/METADATA
sonar_api_wrapper-1.3.0.dist-info/WHEEL
sonar_api_wrapper-1.3.0.dist-info/licenses/LICENSE
sonar_api_wrapper-1.3.0.dist-info/RECORD
