Metadata-Version: 2.3
Name: sonar-api-wrapper
Version: 1.3.0
Summary: Sonar API Wrapper - a Sonarqube api wrapper
Project-URL: Homepage, https://github.com/AlessandroStaffolani/sonar-api-wrapper
Project-URL: Repository, https://github.com/AlessandroStaffolani/sonar-api-wrapper.git
Author-email: Alessandro Staffolani <alestam93@gmail.com>
License: MIT License
License-File: LICENSE
Keywords: sonar,sonarqube
Classifier: Development Status :: 2 - Pre-Alpha
Classifier: Intended Audience :: Developers
Classifier: License :: OSI Approved :: MIT License
Classifier: Natural Language :: English
Classifier: Operating System :: OS Independent
Classifier: Programming Language :: Python :: 3.9
Requires-Python: >=3.8
Requires-Dist: requests
Provides-Extra: dev
Requires-Dist: build; extra == 'dev'
Requires-Dist: coverage[toml]; extra == 'dev'
Requires-Dist: pytest; extra == 'dev'
Requires-Dist: pytest-cov; extra == 'dev'
Requires-Dist: twine; extra == 'dev'
